iduoliao_ml/__init__.py
iduoliao_ml/data/__init__.py
iduoliao_ml/data/data.py
iduoliao_ml/data/dataV2.py
iduoliao_ml/data/worksPersonas.py
iduoliao_ml/dataDispose/__init__.py
iduoliao_ml/dataDispose/subject.py
iduoliao_ml/dataDispose/works.py
iduoliao_ml/es/__init__.py
iduoliao_ml/filterPool/__init__.py
iduoliao_ml/filterPool/bftWorks.py
iduoliao_ml/hot/__init__.py
iduoliao_ml/hot/hot.py
iduoliao_ml/ilog/__init__.py
iduoliao_ml/imatrix/__init__.py
iduoliao_ml/itemCF/__init__.py
iduoliao_ml/recommend/__init__.py
iduoliao_ml/test/__init__.py
iduoliao_ml-1.0.335.dist-info/LICENSE
iduoliao_ml-1.0.335.dist-info/METADATA
iduoliao_ml-1.0.335.dist-info/WHEEL
iduoliao_ml-1.0.335.dist-info/top_level.txt
iduoliao_ml-1.0.335.dist-info/RECORD
