Metadata-Version: 2.1
Name: iduoliao-ml
Version: 1.0.335
Summary: iduoliao machine learning
Home-page: UNKNOWN
Author: legend
Author-email: huangzhen@gzecy.com
License: UNKNOWN
Platform: UNKNOWN
Classifier: Programming Language :: Python :: 2.7
Classifier: License :: OSI Approved :: MIT License
Classifier: Operating System :: OS Independent
